maliput/LICENSE.txt
maliput/__init__.py
maliput/api.cpython-310-x86_64-linux-gnu.so
maliput/math.cpython-310-x86_64-linux-gnu.so
maliput/plugin.cpython-310-x86_64-linux-gnu.so
maliput/utility.cpython-310-x86_64-linux-gnu.so
maliput.egg-info/PKG-INFO
maliput.egg-info/SOURCES.txt
maliput.egg-info/dependency_links.txt
maliput.egg-info/top_level.txt
maliput.libs/libgomp-e985bcbb.so.1.0.0
maliput.libs/libmaliput_api-9fa978c4.so
maliput.libs/libmaliput_common-fe7fbc34.so
maliput.libs/libmaliput_geometry_base-114f9523.so
maliput.libs/libmaliput_math-ddc7ac29.so
maliput.libs/libmaliput_plugin-93f25f40.so
maliput.libs/libmaliput_routing-e709a88a.so
maliput.libs/libmaliput_utility-64fb7e3c.so
maliput-1.8.2.dist-info/METADATA
maliput-1.8.2.dist-info/WHEEL
maliput-1.8.2.dist-info/top_level.txt
maliput-1.8.2.dist-info/RECORD
