Metadata-Version: 2.4
Name: maliput
Version: 1.8.2
Summary: Python bindings for the maliput library.
Home-page: https://github.com/maliput/maliput_py
Author: Franco Cipollone
Keywords: maliput
Requires-Python: >=3.8
Dynamic: author
Dynamic: home-page
Dynamic: keywords
Dynamic: requires-python
Dynamic: summary
